detetime/A1.py
detetime/A10.py
detetime/A2.py
detetime/A3.py
detetime/A4.py
detetime/A5.py
detetime/A6.py
detetime/A7.py
detetime/A8.py
detetime/A9.py
detetime/__init__.py
detetime-5.6.dist-info/licenses/LICENSE.txt
detetime-5.6.dist-info/METADATA
detetime-5.6.dist-info/WHEEL
detetime-5.6.dist-info/top_level.txt
detetime-5.6.dist-info/RECORD
