Metadata-Version: 2.4
Name: detetime
Version: 5.6
Summary: This package provides a DateTime data type, as known from Zope. Unless you need to communicate with Zope APIs, you're probably better off using Python's built-in datetime module.
Author: DateTime
Author-email: date-zope-dev@zope.org
Classifier: Programming Language :: Python :: 3
Classifier: License :: OSI Approved :: MIT License
Classifier: Operating System :: OS Independent
License-File: LICENSE.txt
Dynamic: author
Dynamic: author-email
Dynamic: classifier
Dynamic: license-file
Dynamic: summary
